epic/sql/__init__.py
epic/sql/bigquery/__init__.py
epic/sql/bigquery/ipythonmagic.py
epic/sql/bigquery/query.py
epic/sql/bigquery/temptable.py
epic/sql/general.py
epic_sql-1.1.0.dist-info/LICENSE.md
epic_sql-1.1.0.dist-info/METADATA
epic_sql-1.1.0.dist-info/WHEEL
epic_sql-1.1.0.dist-info/RECORD
