Metadata-Version: 2.1
Name: epic-sql
Version: 1.1.0
Summary: Conveniences for working with SQL
Home-page: https://github.com/epic-framework/epic-sql
License: MIT
Author: Yonatan Perry, Assaf Ben-David
Requires-Python: >=3.10,<4.0
Classifier: License :: OSI Approved :: MIT License
Classifier: Programming Language :: Python :: 3
Classifier: Programming Language :: Python :: 3.10
Classifier: Programming Language :: Python :: 3.11
Classifier: Programming Language :: Python :: 3.12
Classifier: Programming Language :: Python :: 3.13
Provides-Extra: bigquery
Requires-Dist: epic-common (>=1.0.12,<2.0.0)
Requires-Dist: epic-jupyter (>=1.0.5,<2.0.0) ; extra == "bigquery"
Requires-Dist: google-api-core (>=2.24.0,<3.0.0) ; extra == "bigquery"
Requires-Dist: google-cloud-bigquery (>=3.27.0,<4.0.0) ; extra == "bigquery"
Requires-Dist: pandas (>=2.2.3,<3.0.0)
Requires-Dist: tqdm (>=4.67.1,<5.0.0) ; extra == "bigquery"
Project-URL: Repository, https://github.com/epic-framework/epic-sql
